README.md
setup.py
src/vdk/plugin/storage/database_storage.py
src/vdk/plugin/storage/file_storage.py
src/vdk/plugin/storage/plugin_entry.py
src/vdk/plugin/storage/storage.py
src/vdk_storage.egg-info/PKG-INFO
src/vdk_storage.egg-info/SOURCES.txt
src/vdk_storage.egg-info/dependency_links.txt
src/vdk_storage.egg-info/entry_points.txt
src/vdk_storage.egg-info/requires.txt
src/vdk_storage.egg-info/top_level.txt
tests/test_plugin.py