Metadata-Version: 2.1
Name: vdk-storage
Version: 0.1.0
Summary: Library for access to different managed storages
Home-page: https://github.com/vmware/versatile-data-kit
Project-URL: Documentation, https://github.com/vmware/versatile-data-kit/tree/main/projects/vdk-plugins/vdk-storage
Project-URL: Source Code, https://github.com/vmware/versatile-data-kit/tree/main/projects/vdk-plugins/vdk-storage
Project-URL: Bug Tracker, https://github.com/vmware/versatile-data-kit/issues/new/choose
Classifier: Development Status :: 2 - Pre-Alpha
Classifier: License :: OSI Approved :: Apache Software License
Classifier: Programming Language :: Python :: 3.7
Classifier: Programming Language :: Python :: 3.8
Classifier: Programming Language :: Python :: 3.9
Classifier: Programming Language :: Python :: 3.10
Classifier: Programming Language :: Python :: 3.11
Requires-Dist: vdk-core
